Metadata-Version: 1.1
Name: opportunistikapacity
Version: 0.0.1
Summary: A simple library to compute the contact capacity in mobility/contact traces
Home-page: https://github.com/Bertier/OpportunistiKapacity
Author: Clement Bertier
Author-email: clement.bertier@lip6.fr
License: MIT
Download-URL: https://github.com/Bertier/OpportunistiKapacity/archive/v0.0.1.tar.gz
Keywords: CONTACT,OPPORTUNISTIC,CAPACITY,MOBILITY,DATA,TRACE,VANET,MANET
Platform: UNKNOWN
Classifier: Development Status :: 3 - Alpha
Classifier: Intended Audience :: Science/Research
Classifier: Topic :: Scientific/Engineering
Classifier: License :: OSI Approved :: MIT License
Classifier: Programming Language :: Python :: 3
Classifier: Programming Language :: Python :: 3.5
Classifier: Programming Language :: Python :: 3.6
